pmcli.py
pmcli-0.2.9.dist-info/entry_points.txt
pmcli-0.2.9.dist-info/LICENSE.md
pmcli-0.2.9.dist-info/WHEEL
pmcli-0.2.9.dist-info/METADATA
pmcli-0.2.9.dist-info/RECORD
