Metadata-Version: 2.1
Name: pmcli
Version: 0.2.9
Summary: DISCONTINUED. TRY PASSRACK INSTEAD. https://pypi.org/project/passrack/
Home-page: https://github.com/AvanindraC/PMCLI
License: MIT
Keywords: PMCLI
Author: Avanindra Chakraborty
Author-email: avanindra.d2.chakraborty@gmail.com
Requires-Python: >=3.7,<4.0
Classifier: License :: OSI Approved :: MIT License
Classifier: Operating System :: OS Independent
Classifier: Programming Language :: Python :: 3
Classifier: Programming Language :: Python :: 3.6
Classifier: Programming Language :: Python :: 3.7
Classifier: Programming Language :: Python :: 3.8
Classifier: Programming Language :: Python :: 3.9
Requires-Dist: click (>=8.0.1,<9.0.0)
Requires-Dist: click-help-colors (>=0.9,<0.10)
Requires-Dist: cryptocode (>=0.1,<0.2)
Requires-Dist: pyfiglet (>=0.8.post1,<0.9)
Project-URL: Repository, https://github.com/AvanindraC/PMCLI
